{
  "url": "https://www.elobservador.com.uy/nota/menopausia-habitos-y-tratamientos-para-potenciar-la-sexualidad-202422294432",
  "title": "Menopausia: hábitos y tratamientos para potenciar la sexualidad",
  "description": "Claudia Andrea Quezada Bascuñán, Asunción Ferri Morales y Cristina Lirio Moreno, The ConversationAl hablar de menopausia, lo primero que se nos viene a la cabeza es el declive sexual. Pero este proceso por el...",
  "links": [
    "https://www.elobservador.com.uy/nota/menopausia-habitos-y-tratamientos-para-potenciar-la-sexualidad-202422294432",
    "https://www.elobservador.com.uy/nota/menopausia-habitos-y-tratamientos-para-potenciar-la-sexualidad-202422294432/amp"
  ],
  "image": "https://cdn.elobservador.com.uy/022024/1708605854331.jpg?&cw=600&ch=365",
  "content": "<p><em><strong>Claudia Andrea Quezada Bascuñán, Asunción Ferri Morales y Cristina Lirio Moreno, The Conversation</strong></em></p><div><p>Al hablar de menopausia, lo primero que se nos viene a la cabeza es el declive sexual. Pero este proceso por el que pasan todas las mujeres no debería interpretarse así, sino como una nueva etapa por descubrir, un tiempo de transición y de autocuidado. Eso no implica que no sea interesante contar con tratamientos para mantener la función sexual, como veremos a continuación.</p><h3>Una pausa en el camino</h3><p>La menopausia, el cese del sangrado de menstruación durante un período continuo de al menos doce meses, se origina por la reducción de hormonas ováricas, en particular de estrógeno y progesterona. En ocasiones, también la puede desencadenar precozmente algún procedimiento médico, como la extirpación quirúrgica de los ovarios o la radioterapia dirigida a la región pélvica.</p><p>El cambio hormonal provoca modificaciones no solo en la anatomía genital, sino también a nivel mental y emocional. En los genitales, es evidente la pérdida de elasticidad y la sequedad vaginal debido a la reducción del flujo sanguíneo. Las mujeres pueden observarse estos cambios con ayuda de un espejo.</p><p>También hay modificaciones no detectables a simple vista. La microbiota de la vagina, formada por microorganismos que protegen de infecciones, disminuye y altera el ph vaginal, que es la principal causa de candidiasis (infección por hongos) repetitiva.</p><p>El deseo o libido también se ve afectado, probablemente por las dificultades en la penetración. Síntomas como la sequedad, la irritación o el ardor forman un círculo vicioso de dolor.</p><p>Al conjunto de estos cambios y molestias genitales, junto con las alteraciones miccionales, se les denomina “síndrome genitourinario de la menopausia”, y deterioran considerablemente la calidad de vida de las mujeres afectadas.</p><h3>Entonces, ¿la vida sexual tiene fecha de caducidad?</h3><p>¡Claro que no! El mayor problema es la ausencia de tratamientos, que requieren conocer los síntomas y las repercusiones en la calidad de vida de las afectadas. Hasta el presente año, los profesionales no disponían de un cuestionario de evaluación de los síntomas vaginales que provocan alteraciones sexuales.</p><p>Con el fin de paliar este problema, profesoras de la Facultad de Fisioterapia y Enfermería de la UCLM hemos diseñado un instrumento de evaluación para medir las alteraciones en la penetración vaginal. El objetivo es que los sanitarios puedan valorar y hacer tratamientos específicos para cada mujer en particular.</p><h3>Una vez detectado el problema ¿qué hacemos?</h3><p>Comencemos por algunos hábitos sencillos que pueden ayudar a dar la vuelta a los síntomas:</p><ul><li><p><strong>Cuidar la higiene íntima</strong>. Es vital. La zona perineal se debe lavar solo con agua o utilizando algún jabón íntimo con ph ácido. Este tipo de productos contienen el mismo ph que debería tener la vulva, factor que evita el aumento de la sequedad y el prurito o la picazón. En cualquier caso, hay que descartar el jabón de higiene corporal.</p></li><li><p><strong>Vestir con comodidad.</strong> La ropa interior de algodón permite que no se acumule la humedad en la vulva y favorece la estabilidad de la microbiota.</p></li><li><p><strong>Usar lubricante vaginal.</strong> Su principal función es disminuir la fricción poducida por la sequedad vaginal, lo que puede aliviar el dolor y la irritación. El ph del lubricante siempre debe estar entre 3,8 y 4,5, y la osmolaridad (concentración de partículas disueltas en la solución), por debajo de los 370 mOsm/kg.</p></li></ul><h3>Dos terapias innovadoras</h3><p>También existen tratamientos no invasivos que están demostrando cambios efectivos y a largo plazo en la salud sexual de las mujeres con menopausia. Destacan dos de ellos:</p><ul><li><p><strong>Láser de CO₂ vaginal</strong>. Se ha revelado como una opción revolucionaria. Sus resultados se deben a la microablación, procedimiento médico que destruye de forma controlada el tejido de las paredes vaginales. Esta técnica estimula la producción de colágeno y ayuda a la regeneración del tejido, provocando un auténtico “efecto antienvejecimiento” en la vagina</p><p>Estudios recientes han demostrado que el láser puede restaurar el epitelio vaginal, y también se han observado mejoras en la flora vaginal, lo que favorece la reducción de la sequedad. Existe una limitación: de momento, su elevado coste impide que sea accesible para todas las mujeres.</p></li><li><p><strong>Radiofrecuencia no ablativa</strong>. Es administrada con un dispositivo que emite ondas electromagnéticas que generan calor. Cuando la temperatura alcanza los 40 °C-41 ºC, se activan unas células llamadas fibroblastos para producir más colágeno.</p><p>Esta técnica es menos invasiva que el láser de CO₂ vaginal. Actualmente se están estudiando los prometedores resultados de este tratamiento, administrado por fisioterapeutas especializados en salud pélvica.</p></li></ul><h3>Para no olvidar</h3><p>Recordémoslo: la menopausia no es sinónimo de declive en la vida sexual. Conocer los síntomas para diseñar tratamientos específicos es la clave que nos permiten potenciarla. En cualquier caso, esta etapa de la vida femenina ofrece la oportunidad de explorar nuevas formas de autocuidado y función sexual.</p></div>",
  "author": "Redacción",
  "favicon": "https://www.elobservador.com.uy/images/favicons/favicon-16x16.png",
  "source": "elobservador.com.uy",
  "published": "2024-02-22T12:44:32.872Z",
  "ttr": 154,
  "type": "article"
}