{
  "url": "https://www.montevideo.com.uy/Noticias/Un-motociclista-de-85-anos-fallecio-en-choque-con-automovil-uc880305",
  "title": "Un motociclista de 85 años falleció en choque con automóvil",
  "description": "Lamentable                                    Ocurrió en Tacuarembó. Llevaba como acompañante a una mujer de 63 años, quien no sufrió...",
  "links": [
    "https://www.montevideo.com.uy/Noticias/Un-motociclista-de-85-anos-fallecio-en-choque-con-automovil-uc880305",
    "https://www.montevideo.com.uy/Noticias/Un-motociclista-de-85-anos-fallecio-en-choque-con-automovil-uc880305?plantilla=1685&proceso=amp",
    "https://www.montevideo.com.uy/auc.aspx?880305="
  ],
  "image": "https://imagenes.montevideo.com.uy/imgnoticias/201703/_W933_80/603356.jpg",
  "content": "<div>\n                            <article>\n                               <div>\n                                    <p>Lamentable</p>\n                                    <h2>Ocurrió en Tacuarembó. Llevaba como acompañante a una mujer de 63 años, quien no sufrió lesiones.</h2>\n                                </div> \n                                <div>\n                              \t<p>Un hombre de 85 años perdió la vida luego de una colisión\nentre una motocicleta y un auto en la localidad de Tacuarembó.</p><p>Según informara el periodista local Marcos Pereira, el siniestro\nse produjo durante la tarde del martes en la esquina de Manuel Oribe y Joaquín Suárez.</p><p>Alí, y en circunstancias a establecer, la moto conducida por\nel octogenario chocó con un automóvil tripulado por un hombre de 68.</p><p>A raíz del impacto el motorista sufrió graves heridas y fue traslado\nde urgencia a un centro de salud, donde murió poco después de llegar. Levaba\ncomo acompañante a una mujer de 63 años, quien fue asistida en el lugar del\nhecho y dada de alta.</p><p>El falleció fue identificado como Ceferino Baltazar Pérez\nSanjurjo.</p><p>El caso está en manos de la Fiscalía de 2º Turno, que\ndispuso las acciones de rigor.</p>\n                                </div> \n                             <br />\n                            </article> \n                            <br />\n                        </div>",
  "author": "@portalmvd",
  "favicon": "https://www.montevideo.com.uy/favicon/favicon.ico",
  "source": "montevideo.com.uy",
  "published": "",
  "ttr": 31,
  "type": "article"
}