{
  "url": "https://www.montevideo.com.uy/Noticias/-Podria-llegar-a-los-40-grados--Inumet-decidio-extender-por-ocho-dias-la-ola-de-calor-uc878407",
  "title": "“Podría llegar a los 40 grados”: Inumet decidió extender por ocho días la ola de calor",
  "description": "Andá por la sombra                                    Néstor Santayana explicó que no está previsto que las temperaturas bajen en la noche y las mínimas serán de...",
  "links": [
    "https://www.montevideo.com.uy/Noticias/-Podria-llegar-a-los-40-grados--Inumet-decidio-extender-por-ocho-dias-la-ola-de-calor-uc878407",
    "https://www.montevideo.com.uy/Noticias/-Podria-llegar-a-los-40-grados--Inumet-decidio-extender-por-ocho-dias-la-ola-de-calor-uc878407?plantilla=1685&proceso=amp",
    "https://www.montevideo.com.uy/auc.aspx?878407="
  ],
  "image": "https://imagenes.montevideo.com.uy/imgnoticias/202302/_W933_80/833752.jpg",
  "content": "<div>\n                            <article>\n                               <div>\n                                    <p>Andá por la sombra</p>\n                                    <h2>Néstor Santayana explicó que no está previsto que las temperaturas bajen en la noche y las mínimas serán de 25°. \n</h2>\n                                </div> \n                                <div>\n                               <p><span><p>Montevideo Portal</p></span></p><p>El director de Pronósticos del Instituto Nacional de Meteorología (Inumet), Néstor Santayana, anunció que la ola de calor que afecta a Uruguay se extenderá por al menos ocho días más. La determinación, en principio, abarcará también a más departamentos del país. </p><p>De esta manera, el aviso estará vigente hasta el próximo jueves o viernes. “Las temperaturas mínimas van a oscilar entre los 22°C y los 25°, o sea que no es solamente esa temperatura de 34° o 38°”, añadió Santayana.    </p><p>El meteorólogo explicó que las máximas podrían aumentar hasta los 40° en el correr de los ocho días de la ola de calor. Además, puntualizó que está previsto que hacia la noche las temperaturas no disminuyan. </p><p>“El cuerpo, tanto de animales como de seres humanos, empieza a generar un estrés y empieza a tener una afectación”, sostuvo en rueda de prensa.</p>\n                                <p><span><p>Montevideo Portal</p></span></p> \n                                </div> \n                             <br />\n                            </article> \n                            <br />\n                        </div>",
  "author": "@portalmvd",
  "favicon": "https://www.montevideo.com.uy/favicon/favicon.ico",
  "source": "montevideo.com.uy",
  "published": "",
  "ttr": 34,
  "type": "article"
}