{
  "url": "https://ladiaria.com.uy/lento/articulo/2024/2/bancar-los-trapos/",
  "title": "Bancar los trapos",
  "description": "En el gesto periodístico de buscar a quienes hicieron la pancarta del Acto del Obelisco de noviembre de 1983 se puede encontrar bastante más que el registro de una historia. ¿Por qué cuidar un lienzo es preservar la memoria de los encuentros?",
  "links": [
    "https://ladiaria.com.uy/lento/articulo/2024/2/bancar-los-trapos/",
    "https://ladiaria.com.uy/lento/articulo/2024/2/bancar-los-trapos/?display=amp"
  ],
  "image": "https://ladiaria.com.uy/media/photologue/photos/cache/IMG_7827_article_main.jpg?r=s3aQsE6bfcM8T2uV",
  "content": "<div>\n    <article>\n      <div>\n          <p>\n            Publicado el <span>14 de febrero de 2024</span>\n          </p>\n      </div>\n          <h2>En el gesto periodístico de buscar a quienes hicieron la pancarta del Acto del Obelisco de noviembre de 1983 se puede encontrar bastante más que el registro de una historia. ¿Por qué cuidar un lienzo es preservar la memoria de los encuentros?</h2>\n    </article>\n  </div>",
  "author": "https://ladiaria.com.uy/columnista/azul-cordo/",
  "favicon": "https://ladiaria.com.uy/static/favicon-lento.png",
  "source": "ladiaria.com.uy",
  "published": "2024-02-14T00:03:34-03:00",
  "ttr": 10,
  "type": "article"
}