{
  "url": "https://www.elpais.com.uy/sudoku/su-do-ku-8-4-24",
  "title": "Su-do-ku",
  "description": "Rellene con cifras del 1 al 9 los espacios vacíos. Los números no deben repetirse en ninguno de los nueve cuadrados, ni en las horizontales ni en las verticales.        Sudoku.         Solución del Sudoku...",
  "links": [
    "https://www.elpais.com.uy/sudoku/su-do-ku-8-4-24",
    "https://www.elpais.com.uy/sudoku/su-do-ku-8-4-24?_amp=true"
  ],
  "image": "https://imgs.elpais.com.uy/dims4/default/29e2b26/2147483647/strip/true/crop/412x200+0+103/resize/1440x700!/quality/90/?url=https%3A%2F%2Fel-pais-uruguay-production-web.s3.us-east-1.amazonaws.com%2Fbrightspot%2F87%2F0d%2Fc9c7e97843219ed7381114403e29%2Fsudoku.jfif",
  "content": "<div>\n<div>\n<h2>Rellene con cifras del 1 al 9 los espacios vacíos. Los números no deben repetirse en ninguno de los nueve cuadrados, ni en las horizontales ni en las verticales.</h2>\n</div>\n<div>\n<div><figure>\n<picture>\n<img alt=\"Sudoku 8/4\" srcset=\"https://imgs.elpais.com.uy/dims4/default/b391ddf/2147483647/strip/true/crop/409x409+0+0/resize/600x600!/quality/90/?url=https%3A%2F%2Fel-pais-uruguay-production-web.s3.us-east-1.amazonaws.com%2Fbrightspot%2F87%2F0d%2Fc9c7e97843219ed7381114403e29%2Fsudoku.jfif 1x, https://imgs.elpais.com.uy/dims4/default/dbc5e01/2147483647/strip/true/crop/409x409+0+0/resize/1200x1200!/quality/90/?url=https%3A%2F%2Fel-pais-uruguay-production-web.s3.us-east-1.amazonaws.com%2Fbrightspot%2F87%2F0d%2Fc9c7e97843219ed7381114403e29%2Fsudoku.jfif 2x\" src=\"https://imgs.elpais.com.uy/dims4/default/b391ddf/2147483647/strip/true/crop/409x409+0+0/resize/600x600!/quality/90/?url=https%3A%2F%2Fel-pais-uruguay-production-web.s3.us-east-1.amazonaws.com%2Fbrightspot%2F87%2F0d%2Fc9c7e97843219ed7381114403e29%2Fsudoku.jfif\" />\n</picture>\n<p>\n</p><figcaption>Sudoku.</figcaption><p></p>\n</figure>\n</div>\n<div>\n<figure>\n<picture>\n<img alt=\"Sudoku.\" srcset=\"https://imgs.elpais.com.uy/dims4/default/ee8a97b/2147483647/strip/true/crop/436x435+0+0/resize/436x435!/quality/90/?url=https%3A%2F%2Fel-pais-uruguay-production-web.s3.us-east-1.amazonaws.com%2Fbrightspot%2F37%2F7e%2F017ed3fb4506be3783c7fed6ad40%2Fwhatsapp-image-2024-04-07-at-17-35-10.jpeg 1x, https://imgs.elpais.com.uy/dims4/default/1b2de3a/2147483647/strip/true/crop/436x435+0+0/resize/872x870!/quality/90/?url=https%3A%2F%2Fel-pais-uruguay-production-web.s3.us-east-1.amazonaws.com%2Fbrightspot%2F37%2F7e%2F017ed3fb4506be3783c7fed6ad40%2Fwhatsapp-image-2024-04-07-at-17-35-10.jpeg 2x\" src=\"https://imgs.elpais.com.uy/dims4/default/ee8a97b/2147483647/strip/true/crop/436x435+0+0/resize/436x435!/quality/90/?url=https%3A%2F%2Fel-pais-uruguay-production-web.s3.us-east-1.amazonaws.com%2Fbrightspot%2F37%2F7e%2F017ed3fb4506be3783c7fed6ad40%2Fwhatsapp-image-2024-04-07-at-17-35-10.jpeg\" />\n</picture>\n<p>\n</p><figcaption>Solución del Sudoku anterior.</figcaption><p></p>\n</figure>\n</div>\n<div>\n<p>¿Encontraste un error?</p>\n<p>\nReportar\n</p>\n</div>\n</div>\n</div>",
  "author": "",
  "favicon": "https://www.elpais.com.uy/favicon-16x16.png",
  "source": "elpais.com.uy",
  "published": "2024-04-08T07:00:11.601",
  "ttr": 8,
  "type": "article"
}