{
  "url": "https://www.montevideo.com.uy/Noticias/Una-mujer-murio-ahogada-en-una-playa-de-la-ciudad-de-Colonia-uc879390",
  "title": "Una mujer murió ahogada en una playa de la ciudad de Colonia",
  "description": "Triste                                    Su compañero y otros bañistas intentaron reanimarla, pero sus esfuerzos no dieron...",
  "links": [
    "https://www.montevideo.com.uy/Noticias/Una-mujer-murio-ahogada-en-una-playa-de-la-ciudad-de-Colonia-uc879390",
    "https://www.montevideo.com.uy/Noticias/Una-mujer-murio-ahogada-en-una-playa-de-la-ciudad-de-Colonia-uc879390?plantilla=1685&proceso=amp",
    "https://www.montevideo.com.uy/auc.aspx?879390="
  ],
  "image": "https://imagenes.montevideo.com.uy/imgnoticias/202402/_W933_80/871469.jpg",
  "content": "<div>\n                            <article>\n                               <div>\n                                    <p>Triste</p>\n                                    <h2>Su compañero y otros bañistas intentaron reanimarla, pero sus esfuerzos no dieron resultado.</h2>\n                                </div> \n                                <div>\n                              \t<p>Una mujer de 65 años murió ahogada este domingo en la playa\ncoloniense conocida como Los Fogones, no lejos del Real de San Carlos.</p><p>Según informara el portal noticioso <em>Colonia Ya</em>, el hecho\nocurrió en horas de la tarde. El compañero de la mujer la encontró flotando boca\nabajo y sin signos vitales. De inmediato acudió en su ayuda, acción a la que se\nsumaron otras personas que estaban en el lugar, quienes también avisaron al\n911. Sin embargo, pese a los esfuerzos de los bañistas primero y de ambulancia\nde Prefectura después, no fue posible salvar la vida de la mujer.</p><p>Se trata del primer deceso en las playas colonienses en lo\nque va del año.</p><p>La fallecida y su compañero provenían de Montevideo.</p>\n                                </div> \n                             <br />\n                            </article> \n                            <br />\n                        </div>",
  "author": "@portalmvd",
  "favicon": "https://www.montevideo.com.uy/favicon/favicon.ico",
  "source": "montevideo.com.uy",
  "published": "",
  "ttr": 28,
  "type": "article"
}