{
  "url": "https://www.montevideo.com.uy/Noticias/Un-adolescente-de-17-anos-esta-grave-por-ser-baleado-en-su-casa-de-Santa-Catalina-uc878848",
  "title": "Un adolescente de 17 años está grave por ser baleado en su casa de Santa Catalina",
  "description": "No para                                    El hermano de la víctima declaró que estaban en la vivienda cuando un hombre ingresó, y sin mediar palabra, comenzó a...",
  "links": [
    "https://www.montevideo.com.uy/Noticias/Un-adolescente-de-17-anos-esta-grave-por-ser-baleado-en-su-casa-de-Santa-Catalina-uc878848",
    "https://www.montevideo.com.uy/Noticias/Un-adolescente-de-17-anos-esta-grave-por-ser-baleado-en-su-casa-de-Santa-Catalina-uc878848?plantilla=1685&proceso=amp",
    "https://www.montevideo.com.uy/auc.aspx?878848="
  ],
  "image": "https://imagenes.montevideo.com.uy/imgnoticias/201903/_W933_80/685154.jpg",
  "content": "<div>\n                            <article>\n                               <div>\n                                    <p>No para</p>\n                                    <h2>El hermano de la víctima declaró que estaban en la vivienda cuando un hombre ingresó, y sin mediar palabra, comenzó a disparar.\n</h2>\n                                </div> \n                                <div>\n                               <p><span><p>Montevideo Portal</p></span></p><p>Un adolescente de 17 años se encuentra en estado de salud grave tras ser víctima de un ataque a balazos en la madrugada de este martes. El hecho sucedió en Santa Catalina, precisamente en la casa del joven ubicada en Claveles y Burdeos. </p><p>De acuerdo a lo que informó la Policía, en la escena se contaron 18 casquillos de bala y la víctima resultó herida con “múltiples impactos de bala en su cuerpo”. </p><p>Según informó Subrayado y confirmó Montevideo Portal con fuentes de la Policía, el hermano del joven declaró que estaban en la vivienda cuando otro hombre forcejeó la puerta hasta que logró entrar. Inmediatamente, sacó un arma y, sin mediar palabra, baleó al adolescente. </p><p>Por el momento se descarta que haya sido un intento de rapiña y la Fiscalía de Homicidios está llevando adelante la indagatoria.</p>\n                                <p><span><p>Montevideo Portal</p></span></p> \n                                </div> \n                             <br />\n                            </article> \n                            <br />\n                        </div>",
  "author": "@portalmvd",
  "favicon": "https://www.montevideo.com.uy/favicon/favicon.ico",
  "source": "montevideo.com.uy",
  "published": "",
  "ttr": 33,
  "type": "article"
}