{
  "url": "https://www.montevideo.com.uy/Noticias/Libertad-preso-mato-a-companero-de-celda-y-lo-arropo-para-que-pareciera-dormido-uc896958",
  "title": "Libertad: preso mató a compañero de celda y lo arropó para que pareciera dormido",
  "description": "Una pesadilla                                    El matador asestó a la víctima numerosas puñaladas con un corte...",
  "links": [
    "https://www.montevideo.com.uy/Noticias/Libertad-preso-mato-a-companero-de-celda-y-lo-arropo-para-que-pareciera-dormido-uc896958",
    "https://www.montevideo.com.uy/Noticias/Libertad-preso-mato-a-companero-de-celda-y-lo-arropo-para-que-pareciera-dormido-uc896958?plantilla=1685&proceso=amp",
    "https://www.montevideo.com.uy/auc.aspx?896958="
  ],
  "image": "https://imagenes.montevideo.com.uy/imgnoticias/202110/_W933_80/778556.jpeg",
  "content": "<div>\n                            <article>\n                               <div>\n                                    <p>Una pesadilla</p>\n                                    <h2>El matador asestó a la víctima numerosas puñaladas con un corte carcelario.</h2>\n                                </div> \n                                <div>\n                              \t<p>Un recluso de 40 años fue asesinado anoche en el Penal de\nLibertad, en el departamento de San José.</p><p>Según crónica publicada por <em>Info Ciudad del Plata</em>, el\nmatador asestó más de quince puñaladas a su compañero de celda, a quien luego\ncubrió con mantas para que los guardias creyeran que dormía.</p><p>Tras constatar el hecho, la policía detuvo al recluso y le\ntomó declaración. En la celda se incautó un corte carcelario que habría sido\nutilizado para cometer el asesinato.</p><p>En la escena trabajó personal de Policía Científica de\nCiudad del Plata.</p><p>De acuerdo con lo informado por el colectivo de familiares\nde presidiarios Fam Pres, el occiso fue identificado como Gustavo Michael\nFigueroa de León.</p>\n                                </div> \n                             <br />\n                            </article> \n                            <br />\n                        </div>",
  "author": "@portalmvd",
  "favicon": "https://www.montevideo.com.uy/favicon/favicon.ico",
  "source": "montevideo.com.uy",
  "published": "",
  "ttr": 26,
  "type": "article"
}