{
  "url": "https://www.montevideo.com.uy/Noticias/Joven-de-21-anos-asesinado-por-su-pareja-de-19-discutian-el-la-agredio-y-ella-lo-apunalo-uc899513",
  "title": "Joven de 21 años asesinado por su pareja de 19: discutían, él la agredió y ella lo apuñaló",
  "description": "Triste                                    El hecho ocurrió en Ciudad de la Costa. La víctima había sido trasladada a un centro de salud, donde se constató allí el...",
  "links": [
    "https://www.montevideo.com.uy/Noticias/Joven-de-21-anos-asesinado-por-su-pareja-de-19-discutian-el-la-agredio-y-ella-lo-apunalo-uc899513",
    "https://www.montevideo.com.uy/Noticias/Joven-de-21-anos-asesinado-por-su-pareja-de-19-discutian-el-la-agredio-y-ella-lo-apunalo-uc899513?plantilla=1685&proceso=amp",
    "https://www.montevideo.com.uy/auc.aspx?899513="
  ],
  "image": "https://imagenes.montevideo.com.uy/imgnoticias/202005/_W933_80/728645.jpg",
  "content": "<div>\n                            <article>\n                               <div>\n                                    <p>Triste</p>\n                                    <h2>El hecho ocurrió en Ciudad de la Costa. La víctima había sido trasladada a un centro de salud, donde se constató allí el fallecimiento.</h2>\n                                </div> \n                                <div>\n                               <p><span><p>Montevideo Portal</p></span></p><p>Un joven de 21 años\nfue asesinado por su pareja, una joven de 19, en Ciudad de la Costa, según informó\nla Jefatura de Policía de Canelones este sábado.</p><p>El hecho ocurrió a la\naltura del kilómetro 21.100 de la ruta Interbalnearia, donde se informó de que había\n“una persona herida de arma blanca”, de acuerdo con la información difundida en\nel parte policial. Los policías fueron hasta ese lugar, pero la víctima había\nsido trasladada por vecinos a un centro de salud, donde se le constató el\nfallecimiento tras ingresar.</p><p>Los efectivos actuantes cuestionaron a la\nnovia del fallecido, que manifestó que “mantuvo una discusión con la víctima,\n[quien] la agredió físicamente y ella lo apuñaló a la altura del pecho”.</p><p>En el caso trabaja personal de la Jefatura de\nPolicía de Canelones, Policía Científica y personal del departamento de\nHomicidios.</p><p>La Fiscalía de Ciudad de la Costa ya fue\nnotificada al respecto y se investiga en el hecho.</p>\n                                <p><span><p>Montevideo Portal</p></span></p> \n                                </div> \n                             <br />\n                            </article> \n                            <br />\n                        </div>",
  "author": "@portalmvd",
  "favicon": "https://www.montevideo.com.uy/favicon/favicon.ico",
  "source": "montevideo.com.uy",
  "published": "",
  "ttr": 37,
  "type": "article"
}