{
  "url": "https://www.montevideo.com.uy/Ciencia-y-Tecnologia/Florida-la-ola-polar-afecto-el-transito-fluvial-de-la-fauna-autoctona-uc893536",
  "title": "Florida: la ola polar afectó el “tránsito fluvial” de la fauna autóctona",
  "description": "Cómo será la laguna                                    Un residente filmó un episodio singular: una nutria cruzando por un arroyo...",
  "links": [
    "https://www.montevideo.com.uy/Ciencia-y-Tecnologia/Florida-la-ola-polar-afecto-el-transito-fluvial-de-la-fauna-autoctona-uc893536",
    "https://www.montevideo.com.uy/Ciencia-y-Tecnologia/Florida-la-ola-polar-afecto-el-transito-fluvial-de-la-fauna-autoctona-uc893536?plantilla=1685&proceso=amp",
    "https://www.montevideo.com.uy/auc.aspx?893536="
  ],
  "image": "https://imagenes.montevideo.com.uy/imgnoticias/202407/_W933_80/887446.jpg",
  "content": "<div>\n                            <article>\n                               <div>\n                                    <p>Cómo será la laguna</p>\n                                    <h2>Un residente filmó un episodio singular: una nutria cruzando por un arroyo congelado.</h2>\n                                </div> \n                                <div>\n                              \t<p>La<a href=\"https://www.montevideo.com.uy/Noticias/Metsul-emitio-un-pronostico-para-Uruguay-y-anuncio-tres-olas-polares-consecutivas-uc893166\" target=\"_blank\"> ola polar</a> que\nse abate sobre el país por estas horas ha traído temperaturas muy bajas,\nincluso comparadas con las de otros inviernos muy rigurosos.</p><p>El frío es especialmente\nintenso en las primeras horas del día. Por ejemplo, esta mañana en el departamento\nde Florida los termómetros bajaron hasta -5 grados Celsius.</p><p>En semejante\ncontexto, un vecino de la zona de Villa Vieja, cerca del límite con el departamento\nde San José, registró un episodio singular: un arroyo se congeló por completo y\nfue cruzado a patitas por una nutria.</p><p>Animal anfibio,\nla nutria suele moverse dentro del agua, pero esta vez las circunstancias la\nobligaron a hacerlo por encima de ella.</p><p>En el video\ndivulgado por TV Florida se ve a la nutria caminar con dificultad sobre la superficie\ncongelada hasta ganar la orilla opuesta del curso de agua. O en este caso, de hielo.</p><blockquote><p>Debido a la helada nutria cruza arroyo corriendo!<br />Vecino nos envía imagen del paraje Villa Vieja donde una nutria cruza el arroyo corriendo debido a su congelamiento.<br />Tremenda helada en el departamento de Florida. <a target=\"_blank\" href=\"https://t.co/zMuZs4881R\">pic.twitter.com/zMuZs4881R</a></p>— Canal TVFlorida (@tvflorida) <a target=\"_blank\" href=\"https://twitter.com/tvflorida/status/1810676293056205054?ref_src=twsrc%5Etfw\">July 9, 2024</a></blockquote> \n                                </div> \n                             <br />\n                            </article> \n                            <p>\n                                <strong>Te puede interesar</strong>\n                                <span>\n                                    <a target=\"_blank\" href=\"https://www.montevideo.com.uy/Noticias/Inumet-registro-minimas-de-6-3-C-y-en-un-departamento-la-sensacion-termica-fue-de-10-C-uc893509\">Inumet registró mínimas de -6,3 °C y en un departamento la sensación térmica fue de -10 °C</a>\n                                </span> \n                            </p> \n                            <br />\n                        </div>",
  "author": "@portalmvd",
  "favicon": "https://www.montevideo.com.uy/favicon/favicon.ico",
  "source": "montevideo.com.uy",
  "published": "",
  "ttr": 44,
  "type": "article"
}