{
  "url": "https://www.montevideo.com.uy/Noticias/Buscan-a-joven-desaparecido-en-ciudad-de-Maldonado-desde-el-viernes-uc900283",
  "title": "Buscan a joven desaparecido en ciudad de Maldonado desde el viernes",
  "description": "Urgente                                    Luis Alberto de León Pintos fue visto por última vez con un jean color azul claro, un buzo color beige y championes...",
  "links": [
    "https://www.montevideo.com.uy/Noticias/Buscan-a-joven-desaparecido-en-ciudad-de-Maldonado-desde-el-viernes-uc900283",
    "https://www.montevideo.com.uy/Noticias/Buscan-a-joven-desaparecido-en-ciudad-de-Maldonado-desde-el-viernes-uc900283?plantilla=1685&proceso=amp",
    "https://www.montevideo.com.uy/auc.aspx?900283="
  ],
  "image": "https://imagenes.montevideo.com.uy/imgnoticias/202409/_W933_80/894992.jpeg",
  "content": "<div>\n                            <article>\n                               <div>\n                                    <p>Urgente</p>\n                                    <h2>Luis Alberto de León Pintos fue visto por última vez con un jean color azul claro, un buzo color beige y championes negros.</h2>\n                                </div> \n                                <div>\n                              \t<p>Luis Alberto De León Pintos, de 21 años, se encuentra desaparecido desde las 21 horas del viernes en la ciudad de Maldonado, según informó la Jefatura de Policía.</p><p>El joven mide 1.60m, es de tez trigueño, ojos marrones, cabello color negro y complexión delgada. Tiene un tatuaje en el cuello del lado derecho en forma de rayo.</p><p>El día de su desaparición vestía un jean color azul claro, un buzo color beige y championes negros.</p><p>Ante cualquier información, la Jefatura de Policía de Maldonado pide comunicarse al Servicio de Emergencias al 911 o dirigirse a la seccional más cercana.</p>\n                                </div> \n                             <br />\n                            </article> \n                            <p>\n                                <strong>Te puede interesar</strong>\n                                <span>\n                                    <a target=\"_blank\" href=\"https://www.montevideo.com.uy/Noticias/Familiares-y-amigos-buscan-a-Angela-Acuna-desparecida-este-viernes-en-Parque-Batlle-uc900257\">Familiares y amigos buscan a Ángela Acuña, desparecida este viernes en Parque Batlle</a>\n                                </span> \n                            </p> \n                            <br />\n                        </div>",
  "author": "@portalmvd",
  "favicon": "https://www.montevideo.com.uy/favicon/favicon.ico",
  "source": "montevideo.com.uy",
  "published": "",
  "ttr": 28,
  "type": "article"
}