{
  "url": "https://www.montevideo.com.uy/Noticias/Hombre-murio-acribillado-en-barrio-Marconi-le-dispararon-catorce-veces-uc885917",
  "title": "Hombre murió acribillado en barrio Marconi: le dispararon catorce veces",
  "description": "Fuego a discreción                                    El occiso tenía antecedentes penales. La policía procura identificar a los...",
  "links": [
    "https://www.montevideo.com.uy/Noticias/Hombre-murio-acribillado-en-barrio-Marconi-le-dispararon-catorce-veces-uc885917",
    "https://www.montevideo.com.uy/Noticias/Hombre-murio-acribillado-en-barrio-Marconi-le-dispararon-catorce-veces-uc885917?plantilla=1685&proceso=amp",
    "https://www.montevideo.com.uy/auc.aspx?885917="
  ],
  "image": "https://imagenes.montevideo.com.uy/imgnoticias/201610/_W933_80/583664.jpg",
  "content": "<div>\n                            <article>\n                               <div>\n                                    <p>Fuego a discreción</p>\n                                    <h2>El occiso tenía antecedentes penales. La policía procura identificar a los matadores.</h2>\n                                </div> \n                                <div>\n                              \t<p>El barrio Marconi fue escenario durante la pasada noche de\nun episodio violento en el que un hombre perdió la vida.</p><p>Según informara el noticiero <em>Subrayado</em>, el cuerpo fue\nencontrado en Juan Acosta y Pasaje B. Hasta allí habrían llegado dos sujetos en\nmoto que, tras echar pie a tierra, habrían disparado contra la víctima.</p><p>En la escena se encontraron catorce casquillos de balas calibre\nnueve milímetros. Varios de estos proyectiles impactaron en el agredido.</p><p>El occiso, cuya identidad no se divulgó, tenía 31 años y antecedentes\npenales.</p><p>La policía investiga este nuevo hecho de violencia, cuyas\ncaracterísticas sugieren un ajuste de cuentas.</p>\n                                </div> \n                             <br />\n                            </article> \n                            <br />\n                        </div>",
  "author": "@portalmvd",
  "favicon": "https://www.montevideo.com.uy/favicon/favicon.ico",
  "source": "montevideo.com.uy",
  "published": "",
  "ttr": 23,
  "type": "article"
}