{
  "url": "https://ladiaria.com.uy/mundo/articulo/2024/2/esperanza-martinez-parece-que-se-estuviera-midiendo-hasta-que-punto-tolera-la-sociedad-paraguaya-en-su-conjunto-el-avance-del-autoritarismo/",
  "title": "Esperanza Martínez: “Parece que se estuviera midiendo hasta qué punto tolera la sociedad paraguaya en su conjunto el avance del autoritarismo”",
  "description": "Foto:Honorable Cámara de Senadores de la República de Paraguay                                                                      Publicado el 17 de febrero de 2024                               ...",
  "links": [
    "https://ladiaria.com.uy/mundo/articulo/2024/2/esperanza-martinez-parece-que-se-estuviera-midiendo-hasta-que-punto-tolera-la-sociedad-paraguaya-en-su-conjunto-el-avance-del-autoritarismo/",
    "https://ladiaria.com.uy/mundo/articulo/2024/2/esperanza-martinez-parece-que-se-estuviera-midiendo-hasta-que-punto-tolera-la-sociedad-paraguaya-en-su-conjunto-el-avance-del-autoritarismo/?display=amp"
  ],
  "image": "https://ladiaria.com.uy/media/photologue/photos/cache/GGYVqsbWoAAp6FK_article_main.jpeg?r=pASkHLw1W5dvR9ww",
  "content": "<div>\n    <article>\n            <div>\n              <figure>\n                <picture>\n                  <source srcset=\"https://ladiaria.com.uy/media/photologue/photos/cache/GGYVqsbWoAAp6FK_1200w.jpeg\" media=\"(min-width: 1000px)\"></source>\n                  <source srcset=\"https://ladiaria.com.uy/media/photologue/photos/cache/GGYVqsbWoAAp6FK_900w.jpeg\" media=\"(min-width: 700px)\"></source>\n                  <source srcset=\"https://ladiaria.com.uy/media/photologue/photos/cache/GGYVqsbWoAAp6FK_700w.jpeg\" media=\"(min-width: 0px)\"></source>\n                </picture>\n                <figcaption>\n                  <p>Foto:Honorable Cámara de Senadores de la República de Paraguay</p>\n                </figcaption>\n              </figure>\n            </div>\n      <div>\n          <p>\n            Publicado el <span>17 de febrero de 2024</span>\n          </p>\n        <div><p>\n              Escribe\n                <span><a target=\"_blank\" href=\"https://ladiaria.com.uy/periodista/gonzalo-giuria/\">Gonzalo Giuria</a></span>\n               <span>en </span>\n            <span>\n                <a target=\"_blank\" href=\"https://ladiaria.com.uy/seccion/america/\">América</a>\n            </span>\n        </p></div>\n          <div>\n            <svg width=\"16\" height=\"16\">\n            </svg> <p><span>8 minutos</span> de lectura\n          </p></div>\n      </div>\n          <h2>Entrevista con la senadora del Frente Guasú.</h2>\n            <p>La que está finalizando fue una semana muy agitada en el ambiente político de Paraguay. Luego de un proceso plagado de irregularidades, el miércoles, la mayor parte de la bancada…</p>\n<div>\n  <p>Para seguir leyendo ingresá o suscribite</p>\n  <div>\n    <div>\n      <p><a target=\"_blank\" href=\"https://ladiaria.com.uy/usuarios/suscribite/DDIGM/?utm_source=web&amp;utm_medium=paywall\">\n        Suscribite <i>por $195/mes</i>\n      </a>\n    </p></div>\n    <p>Si ya tenés una cuenta</p>\n    <div>\n      <p><a target=\"_blank\" href=\"https://ladiaria.com.uy/usuarios/entrar/?next=/mundo/articulo/2024/2/esperanza-martinez-parece-que-se-estuviera-midiendo-hasta-que-punto-tolera-la-sociedad-paraguaya-en-su-conjunto-el-avance-del-autoritarismo/\">ingresá</a>\n    </p></div>\n    <p>\n      o\n      <a target=\"_blank\" href=\"https://ladiaria.com.uy/usuarios/registrate/\">registrate</a>\n      para acceder a 6 artículos gratis por mes\n    </p>\n  </div>\n</div>\n    </article>\n  </div>",
  "author": "https://ladiaria.com.uy/periodista/gonzalo-giuria/",
  "favicon": "https://ladiaria.com.uy/static/meta/la-diaria-favicon-16x16.png",
  "source": "ladiaria.com.uy",
  "published": "2024-02-17T01:47:38-03:00",
  "ttr": 18,
  "type": "article"
}